mongoct/__init__.py
mongoct/cli.py
mongoct-0.1.2.dist-info/METADATA
mongoct-0.1.2.dist-info/RECORD
mongoct-0.1.2.dist-info/WHEEL
mongoct-0.1.2.dist-info/entry_points.txt
mongoct-0.1.2.dist-info/top_level.txt
